orunnerpool/__init__.py
orunnerpool/__main__.py
orunnerpool/cli.py
orunnerpool/setup.py
orunnerpool/worker.py
orunnerpool-0.1.3.dist-info/LICENSE
orunnerpool-0.1.3.dist-info/METADATA
orunnerpool-0.1.3.dist-info/WHEEL
orunnerpool-0.1.3.dist-info/entry_points.txt
orunnerpool-0.1.3.dist-info/top_level.txt
orunnerpool-0.1.3.dist-info/RECORD
