Metadata-Version: 2.2
Name: orunnerpool
Version: 0.1.3
Summary: Worker client for the ORunner Pool project
Author: ORunner Pool Team
License: MIT
Project-URL: Homepage, https://orunnerpool.com
Project-URL: Bug Tracker, https://github.com/aaronfc/orunnerpool-worker/issues
Project-URL: Source Code, https://github.com/aaronfc/orunnerpool-worker
Classifier: Programming Language :: Python :: 3
Classifier: License :: OSI Approved :: MIT License
Classifier: Operating System :: OS Independent
Requires-Python: >=3.10
License-File: LICENSE
Requires-Dist: requests>=2.28.0
Requires-Dist: configparser>=5.3.0
